heartandsole/__init__.py
heartandsole/util.py
heartandsole/api/__init__.py
heartandsole/api/extensions/__init__.py
heartandsole/compat/__init__.py
heartandsole/compat/_optional.py
heartandsole/core/__init__.py
heartandsole/core/activity.py
heartandsole/core/field.py
heartandsole/core/fields/__init__.py
heartandsole/core/fields/base.py
heartandsole/core/fields/cadence.py
heartandsole/core/fields/distance.py
heartandsole/core/fields/elevation.py
heartandsole/core/fields/grade.py
heartandsole/core/fields/heartrate.py
heartandsole/core/fields/position.py
heartandsole/core/fields/speed.py
heartandsole/core/fields/time.py
heartandsole/core/fields/timestamp.py
tests/__init__.py
tests/test_activity.py
tests/test_fields.py
tests/test_filereaders.py
tests/test_optional_dependency.py
tests/test_register_field.py
heartandsole-0.0.24.dist-info/LICENSE
heartandsole-0.0.24.dist-info/METADATA
heartandsole-0.0.24.dist-info/WHEEL
heartandsole-0.0.24.dist-info/top_level.txt
heartandsole-0.0.24.dist-info/RECORD
