Metadata-Version: 2.1
Name: heartandsole
Version: 0.0.24
Summary: Python library for analysis of running activity data
Home-page: https://github.com/aaron-schroeder/heartandsole
Author: Aaron Schroeder
Author-email: aaron@trailzealot.com
License: MIT License
Project-URL: Documentation, https://heartandsole.readthedocs.io/en/stable/
Classifier: Programming Language :: Python :: 3
Classifier: Programming Language :: Python :: 3.7
Classifier: Programming Language :: Python :: 3.8
Classifier: Programming Language :: Python :: 3.9
Classifier: Programming Language :: Python :: 3.10
Classifier: Programming Language :: Python :: 3.11
Classifier: License :: OSI Approved :: MIT License
Requires-Python: >=3.7
License-File: LICENSE
Requires-Dist: numpy (>=1.15)
Requires-Dist: pandas (>=1.0.0)
